ivwrapper/__init__.py
ivwrapper/ivwrapper.py
ivwrapper-1.4.1.dist-info/METADATA
ivwrapper-1.4.1.dist-info/WHEEL
ivwrapper-1.4.1.dist-info/top_level.txt
ivwrapper-1.4.1.dist-info/RECORD
