Metadata-Version: 2.1
Name: ivwrapper
Version: 1.4.1
Summary: Asynchroniczny wrapper dla api ivall'a.
Home-page: https://github.com/Nohet/ivwrapper
Author: Nohet
Author-email: igorczupryniak503@gmail.com
License: MIT
Keywords: api,ivall api wrapper,wrapper
Platform: UNKNOWN
Classifier: Development Status :: 3 - Alpha
Classifier: Intended Audience :: Developers
Classifier: License :: OSI Approved :: MIT License
Classifier: Programming Language :: Python :: 3
Requires-Dist: aiohttp
